Metadata-Version: 2.1
Name: paramiko-fork
Version: 2.7.4
Summary: SSH2 protocol library
Home-page: https://github.com/paramiko/paramiko/
Author: Jeff Forcier
Author-email: jeff@bitprophet.org
License: LGPL
Platform: Posix; MacOS X; Windows
Classifier: Development Status :: 5 - Production/Stable
Classifier: Intended Audience :: Developers
Classifier: License :: OSI Approved :: GNU Library or Lesser General Public License (LGPL)
Classifier: Operating System :: OS Independent
Classifier: Topic :: Internet
Classifier: Topic :: Security :: Cryptography
Classifier: Programming Language :: Python
Classifier: Programming Language :: Python :: 2
Classifier: Programming Language :: Python :: 2.7
Classifier: Programming Language :: Python :: 3
Classifier: Programming Language :: Python :: 3.4
Classifier: Programming Language :: Python :: 3.5
Classifier: Programming Language :: Python :: 3.6
Classifier: Programming Language :: Python :: 3.7
Classifier: Programming Language :: Python :: 3.8
Requires-Dist: bcrypt (>=3.1.3)
Requires-Dist: cryptography (>=2.5)
Requires-Dist: pynacl (>=1.0.1)
Provides-Extra: all
Requires-Dist: pyasn1 (>=0.1.7) ; extra == 'all'
Requires-Dist: pynacl (>=1.0.1) ; extra == 'all'
Requires-Dist: bcrypt (>=3.1.3) ; extra == 'all'
Requires-Dist: invoke (>=1.3) ; extra == 'all'
Requires-Dist: gssapi (>=1.4.1) ; (platform_system != "Windows") and extra == 'all'
Requires-Dist: pywin32 (>=2.1.8) ; (platform_system == "Windows") and extra == 'all'
Provides-Extra: ed25519
Requires-Dist: pynacl (>=1.0.1) ; extra == 'ed25519'
Requires-Dist: bcrypt (>=3.1.3) ; extra == 'ed25519'
Provides-Extra: gssapi
Requires-Dist: pyasn1 (>=0.1.7) ; extra == 'gssapi'
Requires-Dist: gssapi (>=1.4.1) ; (platform_system != "Windows") and extra == 'gssapi'
Requires-Dist: pywin32 (>=2.1.8) ; (platform_system == "Windows") and extra == 'gssapi'
Provides-Extra: invoke
Requires-Dist: invoke (>=1.3) ; extra == 'invoke'
